filefrag/__init__.py
filefrag/__main__.py
filefrag/device.py
filefrag/extent.py
filefrag/fie.py
filefrag/filefrag.py
filefrag/filemap.py
filefrag-0.0.2.dist-info/entry_points.txt
filefrag-0.0.2.dist-info/WHEEL
filefrag-0.0.2.dist-info/METADATA
filefrag-0.0.2.dist-info/RECORD
